<?xml version="1.0" encoding="UTF-8"?><lehreroffice xmlns="http://www.lehreroffice.ch/xmlns/lo/2010/definitions-v1" version="2010.1" object="4"><definitions><source><appName>LehrerOffice Easy</appName><appVersion>2013.5.2</appVersion><creationDate>2013-09-29</creationDate><creationTime>21:33:04</creationTime></source><competenceGrids><competenceGrid key="OW_KIGA_GESAMTKATALOG" versionDate="2013-09-16"><gridDefinition><gridName>Kindergarten Gesamtkatalog</gridName><editionDate>2013-09-16</editionDate><author>Kanton Obwalden / Amt für Volks- und Mittelschulen</author><grade>VS</grade><fromClassYear>1</fromClassYear><untilClassYear>2</untilClassYear><curriculum>Kanton OW</curriculum><modifyAllowed>0</modifyAllowed><protected>0</protected><gradingLabels inverted="1"><gradingLabel gradingPos="0" lang="de"><gradingName>nicht beurteilt</gradingName><gradingShortname>-</gradingShortname></gradingLabel><gradingLabel gradingPos="1" lang="de"><gradingName>nicht erreicht</gradingName><gradingShortname>n</gradingShortname></gradingLabel><gradingLabel gradingPos="2" lang="de"><gradingName>teilweise erreicht</gradingName><gradingShortname>t</gradingShortname></gradingLabel><gradingLabel gradingPos="3" lang="de"><gradingName>erreicht</gradingName><gradingShortname>e</gradingShortname></gradingLabel></gradingLabels></gridDefinition><gridItems><gridItem key="AVZ8RWPJP0V" itemKind="competencearea" countEnabled="0" valuesEnabled="0"><itemDefinition><addAllowed>1</addAllowed><hideAllowed>0</hideAllowed><modifyAllowed>0</modifyAllowed></itemDefinition><itemNames><itemName personalForm="0" lang="de">Selbstkompetenz</itemName></itemNames><gridItems><gridItem key="AVZ8RWPLR4X" itemKind="target" countEnabled="1" valuesEnabled="1"><itemDefinition><addAllowed>1</addAllowed><hideAllowed>1</hideAllowed><modifyAllowed>0</modifyAllowed></itemDefinition><itemNames><itemName personalForm="0" lang="de">Bewegungsverhalten</itemName></itemNames><gridItems><gridItem key="AVZ8RWPMTRZ" itemKind="indicator" countEnabled="1" valuesEnabled="1"><itemDefinition><addAllowed>0</addAllowed><hideAllowed>1</hideAllowed><modifyAllowed>1</modifyAllowed></itemDefinition><itemNames><itemName personalForm="0" lang="de">Zeigt harmonisches und der Situation angepasstes Bewegungsverhalten (hüpfen, springen, laufen...) (KG).</itemName></itemNames><itemDescriptions><itemDescription personalForm="0" lang="de">KG</itemDescription></itemDescriptions></gridItem><gridItem key="AVZ8RWPMD337" itemKind="indicator" countEnabled="1" valuesEnabled="1"><itemDefinition><addAllowed>0</addAllowed><hideAllowed>1</hideAllowed><modifyAllowed>1</modifyAllowed></itemDefinition><itemNames><itemName personalForm="0" lang="de">Kann Sehen und Handmotorik übereinstimmen (zielen, fangen) (KG).</itemName></itemNames><itemDescriptions><itemDescription personalForm="0" lang="de">KG</itemDescription></itemDescriptions></gridItem><gridItem key="AVZ8RWPMIU39" itemKind="indicator" countEnabled="1" valuesEnabled="1"><itemDefinition><addAllowed>0</addAllowed><hideAllowed>1</hideAllowed><modifyAllowed>1</modifyAllowed></itemDefinition><itemNames><itemName personalForm="0" lang="de">Die Finger- und Handgeschicklichkeit ist vorhanden (zeichnen, schneiden) (KG).</itemName></itemNames><itemDescriptions><itemDescription personalForm="0" lang="de">KG</itemDescription></itemDescriptions></gridItem><gridItem key="AVZ8RWPMOQ41" itemKind="indicator" countEnabled="1" valuesEnabled="1"><itemDefinition><addAllowed>0</addAllowed><hideAllowed>1</hideAllowed><modifyAllowed>1</modifyAllowed></itemDefinition><itemNames><itemName personalForm="0" lang="de">Ist körperlich dem Alter entsprechend belastbar (KG).</itemName></itemNames><itemDescriptions><itemDescription personalForm="0" lang="de">KG</itemDescription></itemDescriptions></gridItem></gridItems></gridItem><gridItem key="AVZ8RWPRXD54" itemKind="target" countEnabled="1" valuesEnabled="1"><itemDefinition><addAllowed>1</addAllowed><hideAllowed>1</hideAllowed><modifyAllowed>0</modifyAllowed></itemDefinition><itemNames><itemName personalForm="0" lang="de">Wahrnehmungsverhalten</itemName></itemNames><gridItems><gridItem key="AVZ8RWPSRV58" itemKind="indicator" countEnabled="1" valuesEnabled="1"><itemDefinition><addAllowed>0</addAllowed><hideAllowed>1</hideAllowed><modifyAllowed>1</modifyAllowed></itemDefinition><itemNames><itemName personalForm="0" lang="de">Nimmt den Körper differenziert wahr (Körperteile benennen) (KG).</itemName></itemNames><itemDescriptions><itemDescription personalForm="0" lang="de">KG</itemDescription></itemDescriptions></gridItem><gridItem key="AVZ8RWPSV760" itemKind="indicator" countEnabled="1" valuesEnabled="1"><itemDefinition><addAllowed>0</addAllowed><hideAllowed>1</hideAllowed><modifyAllowed>1</modifyAllowed></itemDefinition><itemNames><itemName personalForm="0" lang="de">Nimmt eigene Gefühle und Stimmungen wahr (KG).</itemName></itemNames><itemDescriptions><itemDescription personalForm="0" lang="de">KG</itemDescription></itemDescriptions></gridItem><gridItem key="AVZ8RXOOTN163" itemKind="indicator" countEnabled="1" valuesEnabled="1"><itemDefinition><addAllowed>0</addAllowed><hideAllowed>1</hideAllowed><modifyAllowed>1</modifyAllowed></itemDefinition><itemNames><itemName personalForm="0" lang="de">Kann Wahrnehmungen in den einzelnen Sinnesbereichen unterscheiden (riechen, tasten, hören, sehen, schmecken) (KG).</itemName></itemNames><itemDescriptions><itemDescription personalForm="0" lang="de">KG</itemDescription></itemDescriptions></gridItem></gridItems></gridItem><gridItem key="AVZ8RWPTDY62" itemKind="target" countEnabled="1" valuesEnabled="1"><itemDefinition><addAllowed>1</addAllowed><hideAllowed>1</hideAllowed><modifyAllowed>0</modifyAllowed></itemDefinition><itemNames><itemName personalForm="0" lang="de">Ausdrucksfähigkeit</itemName></itemNames><gridItems><gridItem key="AVZ8RWPTHU64" itemKind="indicator" countEnabled="1" valuesEnabled="1"><itemDefinition><addAllowed>0</addAllowed><hideAllowed>1</hideAllowed><modifyAllowed>1</modifyAllowed></itemDefinition><itemNames><itemName personalForm="0" lang="de">Drückt sich durch Mimik und Gestik vielfältig und verständlich aus (KG).</itemName></itemNames><itemDescriptions><itemDescription personalForm="0" lang="de">KG</itemDescription></itemDescriptions></gridItem><gridItem key="AVZ8RWPTR066" itemKind="indicator" countEnabled="1" valuesEnabled="1"><itemDefinition><addAllowed>0</addAllowed><hideAllowed>1</hideAllowed><modifyAllowed>1</modifyAllowed></itemDefinition><itemNames><itemName personalForm="0" lang="de">Drückt  seine eigenen Gefühle und Empfindungen aus (KG).</itemName></itemNames><itemDescriptions><itemDescription personalForm="0" lang="de">KG</itemDescription></itemDescriptions></gridItem></gridItems></gridItem><gridItem key="AVZ8RWPTX668" itemKind="target" countEnabled="1" valuesEnabled="1"><itemDefinition><addAllowed>1</addAllowed><hideAllowed>1</hideAllowed><modifyAllowed>0</modifyAllowed></itemDefinition><itemNames><itemName personalForm="0" lang="de">Selbständigkeit</itemName></itemNames><gridItems><gridItem key="AVZ8RWPUC670" itemKind="indicator" countEnabled="1" valuesEnabled="1"><itemDefinition><addAllowed>0</addAllowed><hideAllowed>1</hideAllowed><modifyAllowed>1</modifyAllowed></itemDefinition><itemNames><itemName personalForm="0" lang="de">Ist selbständig beim Ausführen von alltäglichen Handlungen (KG).</itemName></itemNames><itemDescriptions><itemDescription personalForm="0" lang="de">KG</itemDescription></itemDescriptions></gridItem><gridItem key="AVZ8RWPUK172" itemKind="indicator" countEnabled="1" valuesEnabled="1"><itemDefinition><addAllowed>0</addAllowed><hideAllowed>1</hideAllowed><modifyAllowed>1</modifyAllowed></itemDefinition><itemNames><itemName personalForm="0" lang="de">Entwickelt eigene Ideen und führt diese aus (KG).</itemName></itemNames><itemDescriptions><itemDescription personalForm="0" lang="de">KG</itemDescription></itemDescriptions></gridItem><gridItem key="AVZ8RWPUOE74" itemKind="indicator" countEnabled="1" valuesEnabled="1"><itemDefinition><addAllowed>0</addAllowed><hideAllowed>1</hideAllowed><modifyAllowed>1</modifyAllowed></itemDefinition><itemNames><itemName personalForm="0" lang="de">Führt Aufgaben zuverlässig aus (KG).</itemName></itemNames><itemDescriptions><itemDescription personalForm="0" lang="de">KG</itemDescription></itemDescriptions></gridItem><gridItem key="AVZ8RWPUYV76" itemKind="indicator" countEnabled="1" valuesEnabled="1"><itemDefinition><addAllowed>0</addAllowed><hideAllowed>1</hideAllowed><modifyAllowed>1</modifyAllowed></itemDefinition><itemNames><itemName personalForm="0" lang="de">Ist motiviert und zeigt Lernwillen (KG).</itemName></itemNames><itemDescriptions><itemDescription personalForm="0" lang="de">KG</itemDescription></itemDescriptions></gridItem></gridItems></gridItem><gridItem key="AVZ8RWQZQH81" itemKind="target" countEnabled="1" valuesEnabled="1"><itemDefinition><addAllowed>1</addAllowed><hideAllowed>1</hideAllowed><modifyAllowed>0</modifyAllowed></itemDefinition><itemNames><itemName personalForm="0" lang="de">Selbstvertrauen</itemName></itemNames><gridItems><gridItem key="AVZ8RWQZX883" itemKind="indicator" countEnabled="1" valuesEnabled="1"><itemDefinition><addAllowed>0</addAllowed><hideAllowed>1</hideAllowed><modifyAllowed>1</modifyAllowed></itemDefinition><itemNames><itemName personalForm="0" lang="de">Kann eigene Stärken und Schwächen einschätzen und damit umgehen (KG).</itemName></itemNames><itemDescriptions><itemDescription personalForm="0" lang="de">KG</itemDescription></itemDescriptions></gridItem><gridItem key="AVZ8RWRAD985" itemKind="indicator" countEnabled="1" valuesEnabled="1"><itemDefinition><addAllowed>0</addAllowed><hideAllowed>1</hideAllowed><modifyAllowed>1</modifyAllowed></itemDefinition><itemNames><itemName personalForm="0" lang="de">Kann sich vor Übergriffen schützen (KG).</itemName></itemNames><itemDescriptions><itemDescription personalForm="0" lang="de">KG</itemDescription></itemDescriptions></gridItem><gridItem key="AVZ8RWRAIH87" itemKind="indicator" countEnabled="1" valuesEnabled="1"><itemDefinition><addAllowed>0</addAllowed><hideAllowed>1</hideAllowed><modifyAllowed>1</modifyAllowed></itemDefinition><itemNames><itemName personalForm="0" lang="de">Arbeitet ohne ständige Bestätigung (KG).</itemName></itemNames><itemDescriptions><itemDescription personalForm="0" lang="de">KG</itemDescription></itemDescriptions></gridItem></gridItems></gridItem><gridItem key="AVZ8RWRABP89" itemKind="target" countEnabled="1" valuesEnabled="1"><itemDefinition><addAllowed>1</addAllowed><hideAllowed>1</hideAllowed><modifyAllowed>0</modifyAllowed></itemDefinition><itemNames><itemName personalForm="0" lang="de">Umgang mit Misserfolg</itemName></itemNames><gridItems><gridItem key="AVZ8RWRAII91" itemKind="indicator" countEnabled="1" valuesEnabled="1"><itemDefinition><addAllowed>0</addAllowed><hideAllowed>1</hideAllowed><modifyAllowed>1</modifyAllowed></itemDefinition><itemNames><itemName personalForm="0" lang="de">Zeigt Durchhaltevermögen bei Misserfolg (KG).</itemName></itemNames><itemDescriptions><itemDescription personalForm="0" lang="de">KG</itemDescription></itemDescriptions></gridItem><gridItem key="AVZ8RWRAMN93" itemKind="indicator" countEnabled="1" valuesEnabled="1"><itemDefinition><addAllowed>0</addAllowed><hideAllowed>1</hideAllowed><modifyAllowed>1</modifyAllowed></itemDefinition><itemNames><itemName personalForm="0" lang="de">Kann Enttäuschungen verbalisieren und verarbeiten (KG).</itemName></itemNames><itemDescriptions><itemDescription personalForm="0" lang="de">KG</itemDescription></itemDescriptions></gridItem><gridItem key="AVZ8RWRARK95" itemKind="indicator" countEnabled="1" valuesEnabled="1"><itemDefinition><addAllowed>0</addAllowed><hideAllowed>1</hideAllowed><modifyAllowed>1</modifyAllowed></itemDefinition><itemNames><itemName personalForm="0" lang="de">Holt bei Schwierigkeiten Hilfe (KG).</itemName></itemNames><itemDescriptions><itemDescription personalForm="0" lang="de">KG</itemDescription></itemDescriptions></gridItem></gridItems></gridItem><gridItem key="AVZ8RWRCZD97" itemKind="target" countEnabled="1" valuesEnabled="1"><itemDefinition><addAllowed>1</addAllowed><hideAllowed>1</hideAllowed><modifyAllowed>0</modifyAllowed></itemDefinition><itemNames><itemName personalForm="0" lang="de">Ausdauer und Konzentrationsfähigkeit</itemName></itemNames><gridItems><gridItem key="AVZ8RWRDE599" itemKind="indicator" countEnabled="1" valuesEnabled="1"><itemDefinition><addAllowed>0</addAllowed><hideAllowed>1</hideAllowed><modifyAllowed>1</modifyAllowed></itemDefinition><itemNames><itemName personalForm="0" lang="de">Beschäftigt sich konzentriert über einen bestimmten Zeitraum (KG).</itemName></itemNames><itemDescriptions><itemDescription personalForm="0" lang="de">KG</itemDescription></itemDescriptions></gridItem><gridItem key="AVZ8RWRDJM101" itemKind="indicator" countEnabled="1" valuesEnabled="1"><itemDefinition><addAllowed>0</addAllowed><hideAllowed>1</hideAllowed><modifyAllowed>1</modifyAllowed></itemDefinition><itemNames><itemName personalForm="0" lang="de">Beendet angefangene Arbeiten in angemessenem Tempo (KG).</itemName></itemNames><itemDescriptions><itemDescription personalForm="0" lang="de">KG</itemDescription></itemDescriptions></gridItem><gridItem key="AVZ8RWRDPV103" itemKind="indicator" countEnabled="1" valuesEnabled="1"><itemDefinition><addAllowed>0</addAllowed><hideAllowed>1</hideAllowed><modifyAllowed>1</modifyAllowed></itemDefinition><itemNames><itemName personalForm="0" lang="de">Gibt nicht auf, wenn etwas schief läuft (KG).</itemName></itemNames><itemDescriptions><itemDescription personalForm="0" lang="de">KG</itemDescription></itemDescriptions></gridItem></gridItems></gridItem></gridItems></gridItem><gridItem key="AVZ8RWRETO105" itemKind="competencearea" countEnabled="0" valuesEnabled="0"><itemDefinition><addAllowed>0</addAllowed><hideAllowed>0</hideAllowed><modifyAllowed>0</modifyAllowed></itemDefinition><itemNames><itemName personalForm="0" lang="de">Sozialkompetenz</itemName></itemNames><gridItems><gridItem key="AVZ8RWRFIN107" itemKind="target" countEnabled="1" valuesEnabled="1"><itemDefinition><addAllowed>1</addAllowed><hideAllowed>1</hideAllowed><modifyAllowed>0</modifyAllowed></itemDefinition><itemNames><itemName personalForm="0" lang="de">Einfühlungsvermögen und Rücksichtnahme</itemName></itemNames><gridItems><gridItem key="AVZ8RWRFQK109" itemKind="indicator" countEnabled="1" valuesEnabled="1"><itemDefinition><addAllowed>0</addAllowed><hideAllowed>1</hideAllowed><modifyAllowed>1</modifyAllowed></itemDefinition><itemNames><itemName personalForm="0" lang="de">Nimmt Gefühle und Bedürfnisse anderer Kinder wahr und berücksichtigt diese (KG).</itemName></itemNames><itemDescriptions><itemDescription personalForm="0" lang="de">KG</itemDescription></itemDescriptions></gridItem><gridItem key="AVZ8RXOOW2167" itemKind="indicator" countEnabled="1" valuesEnabled="1"><itemDefinition><addAllowed>0</addAllowed><hideAllowed>1</hideAllowed><modifyAllowed>1</modifyAllowed></itemDefinition><itemNames><itemName personalForm="0" lang="de">Vermeidet Verhalten, das Mitschüler/innen stört (KG).</itemName></itemNames><itemDescriptions><itemDescription personalForm="0" lang="de">KG</itemDescription></itemDescriptions></gridItem><gridItem key="AVZ8RXOPGG169" itemKind="indicator" countEnabled="1" valuesEnabled="1"><itemDefinition><addAllowed>0</addAllowed><hideAllowed>1</hideAllowed><modifyAllowed>1</modifyAllowed></itemDefinition><itemNames><itemName personalForm="0" lang="de">Übernimmt Arbeiten für die Gemeinschaft (KG).</itemName></itemNames><itemDescriptions><itemDescription personalForm="0" lang="de">KG</itemDescription></itemDescriptions></gridItem></gridItems></gridItem><gridItem key="AVZ8RXIWOV37" itemKind="target" countEnabled="1" valuesEnabled="1"><itemDefinition><addAllowed>1</addAllowed><hideAllowed>1</hideAllowed><modifyAllowed>0</modifyAllowed></itemDefinition><itemNames><itemName personalForm="0" lang="de">Verhalten in der Gemeinschaft</itemName></itemNames><gridItems><gridItem key="AVZ8RXIWY639" itemKind="indicator" countEnabled="1" valuesEnabled="1"><itemDefinition><addAllowed>0</addAllowed><hideAllowed>1</hideAllowed><modifyAllowed>1</modifyAllowed></itemDefinition><itemNames><itemName personalForm="0" lang="de">Bezieht andere Kinder ins Spiel ein und lässt sich einbeziehen (KG).</itemName></itemNames><itemDescriptions><itemDescription personalForm="0" lang="de">KG</itemDescription></itemDescriptions></gridItem><gridItem key="AVZ8RXIWGL41" itemKind="indicator" countEnabled="1" valuesEnabled="1"><itemDefinition><addAllowed>0</addAllowed><hideAllowed>1</hideAllowed><modifyAllowed>1</modifyAllowed></itemDefinition><itemNames><itemName personalForm="0" lang="de">Hält sich an Regeln und Abmachungen (KG).</itemName></itemNames><itemDescriptions><itemDescription personalForm="0" lang="de">KG</itemDescription></itemDescriptions></gridItem><gridItem key="AVZ8RXIWLX43" itemKind="indicator" countEnabled="1" valuesEnabled="1"><itemDefinition><addAllowed>0</addAllowed><hideAllowed>1</hideAllowed><modifyAllowed>1</modifyAllowed></itemDefinition><itemNames><itemName personalForm="0" lang="de">Fühlt sich wohl in einer grösseren Gruppe (KG).</itemName></itemNames><itemDescriptions><itemDescription personalForm="0" lang="de">KG</itemDescription></itemDescriptions></gridItem><gridItem key="AVZ8RXIWRH45" itemKind="indicator" countEnabled="1" valuesEnabled="1"><itemDefinition><addAllowed>0</addAllowed><hideAllowed>1</hideAllowed><modifyAllowed>1</modifyAllowed></itemDefinition><itemNames><itemName personalForm="0" lang="de">Ist emotional dem Alter entsprechend belastbar (KG).</itemName></itemNames><itemDescriptions><itemDescription personalForm="0" lang="de">KG</itemDescription></itemDescriptions></gridItem></gridItems></gridItem><gridItem key="AVZ8RXIWAC47" itemKind="target" countEnabled="1" valuesEnabled="1"><itemDefinition><addAllowed>1</addAllowed><hideAllowed>1</hideAllowed><modifyAllowed>0</modifyAllowed></itemDefinition><itemNames><itemName personalForm="0" lang="de">Kommunikationsfähigkeit</itemName></itemNames><gridItems><gridItem key="AVZ8RXIWJ349" itemKind="indicator" countEnabled="1" valuesEnabled="1"><itemDefinition><addAllowed>0</addAllowed><hideAllowed>1</hideAllowed><modifyAllowed>1</modifyAllowed></itemDefinition><itemNames><itemName personalForm="0" lang="de">Geht auf Mitschüler/innen zu, spielt und redet mit anderen Kindern seiner Klasse (KG).</itemName></itemNames><itemDescriptions><itemDescription personalForm="0" lang="de">KG</itemDescription></itemDescriptions></gridItem><gridItem key="AVZ8RXIWOZ51" itemKind="indicator" countEnabled="1" valuesEnabled="1"><itemDefinition><addAllowed>0</addAllowed><hideAllowed>1</hideAllowed><modifyAllowed>1</modifyAllowed></itemDefinition><itemNames><itemName personalForm="0" lang="de">Teilt eigene Bedürfnisse / Meinungen mit und setzt sich dafür ein (KG).</itemName></itemNames><itemDescriptions><itemDescription personalForm="0" lang="de">KG</itemDescription></itemDescriptions></gridItem><gridItem key="AVZ8RXIWT453" itemKind="indicator" countEnabled="1" valuesEnabled="1"><itemDefinition><addAllowed>0</addAllowed><hideAllowed>1</hideAllowed><modifyAllowed>1</modifyAllowed></itemDefinition><itemNames><itemName personalForm="0" lang="de">Spricht Erwachsene in angemessenem Ton an (KG).</itemName></itemNames><itemDescriptions><itemDescription personalForm="0" lang="de">KG</itemDescription></itemDescriptions></gridItem></gridItems></gridItem><gridItem key="AVZ8RXIXIK56" itemKind="target" countEnabled="1" valuesEnabled="1"><itemDefinition><addAllowed>1</addAllowed><hideAllowed>1</hideAllowed><modifyAllowed>0</modifyAllowed></itemDefinition><itemNames><itemName personalForm="0" lang="de">Umgang mit Konflikten</itemName></itemNames><gridItems><gridItem key="AVZ8RXIXO258" itemKind="indicator" countEnabled="1" valuesEnabled="1"><itemDefinition><addAllowed>0</addAllowed><hideAllowed>1</hideAllowed><modifyAllowed>1</modifyAllowed></itemDefinition><itemNames><itemName personalForm="0" lang="de">Verhandelt in Konfliktsituationen und kann Kompromisse eingehen (KG).</itemName></itemNames><itemDescriptions><itemDescription personalForm="0" lang="de">KG</itemDescription></itemDescriptions></gridItem><gridItem key="AVZ8RXIXT660" itemKind="indicator" countEnabled="1" valuesEnabled="1"><itemDefinition><addAllowed>0</addAllowed><hideAllowed>1</hideAllowed><modifyAllowed>1</modifyAllowed></itemDefinition><itemNames><itemName personalForm="0" lang="de">Setzt sich für andere ein (KG).</itemName></itemNames><itemDescriptions><itemDescription personalForm="0" lang="de">KG</itemDescription></itemDescriptions></gridItem><gridItem key="AVZ8RXIXYB62" itemKind="indicator" countEnabled="1" valuesEnabled="1"><itemDefinition><addAllowed>0</addAllowed><hideAllowed>1</hideAllowed><modifyAllowed>1</modifyAllowed></itemDefinition><itemNames><itemName personalForm="0" lang="de">Löst Konflikte ohne Hilfe von Erwachsenen (KG).</itemName></itemNames><itemDescriptions><itemDescription personalForm="0" lang="de">KG</itemDescription></itemDescriptions></gridItem><gridItem key="AVZ8RXIXDB64" itemKind="indicator" countEnabled="1" valuesEnabled="1"><itemDefinition><addAllowed>0</addAllowed><hideAllowed>1</hideAllowed><modifyAllowed>1</modifyAllowed></itemDefinition><itemNames><itemName personalForm="0" lang="de">Setzt in Konfliktsituationen faire Mittel ein (KG).</itemName></itemNames><itemDescriptions><itemDescription personalForm="0" lang="de">KG</itemDescription></itemDescriptions></gridItem></gridItems></gridItem><gridItem key="AVZ8RXIXK966" itemKind="target" countEnabled="1" valuesEnabled="1"><itemDefinition><addAllowed>1</addAllowed><hideAllowed>1</hideAllowed><modifyAllowed>0</modifyAllowed></itemDefinition><itemNames><itemName personalForm="0" lang="de">Umgang mit Werten</itemName></itemNames><gridItems><gridItem key="AVZ8RXIXSZ68" itemKind="indicator" countEnabled="1" valuesEnabled="1"><itemDefinition><addAllowed>0</addAllowed><hideAllowed>1</hideAllowed><modifyAllowed>1</modifyAllowed></itemDefinition><itemNames><itemName personalForm="0" lang="de">Achtet die im Kindergarten geltenden Werte (KG).</itemName></itemNames><itemDescriptions><itemDescription personalForm="0" lang="de">KG</itemDescription></itemDescriptions></gridItem><gridItem key="AVZ8RXIYF770" itemKind="indicator" countEnabled="1" valuesEnabled="1"><itemDefinition><addAllowed>0</addAllowed><hideAllowed>1</hideAllowed><modifyAllowed>1</modifyAllowed></itemDefinition><itemNames><itemName personalForm="0" lang="de">Kennt Bräuche und Rituale und verhält sich entsprechend (KG).</itemName></itemNames><itemDescriptions><itemDescription personalForm="0" lang="de">KG</itemDescription></itemDescriptions></gridItem></gridItems></gridItem><gridItem key="AVZ8RXIYMQ72" itemKind="target" countEnabled="1" valuesEnabled="1"><itemDefinition><addAllowed>1</addAllowed><hideAllowed>1</hideAllowed><modifyAllowed>0</modifyAllowed></itemDefinition><itemNames><itemName personalForm="0" lang="de">Verständnis für die Verschiedenartigkeit von Menschen</itemName></itemNames><gridItems><gridItem key="AVZ8RXIYSD74" itemKind="indicator" countEnabled="1" valuesEnabled="1"><itemDefinition><addAllowed>0</addAllowed><hideAllowed>1</hideAllowed><modifyAllowed>1</modifyAllowed></itemDefinition><itemNames><itemName personalForm="0" lang="de">Interessiert sich für andere Menschen (KG).</itemName></itemNames><itemDescriptions><itemDescription personalForm="0" lang="de">KG</itemDescription></itemDescriptions></gridItem><gridItem key="AVZ8RXIYW876" itemKind="indicator" countEnabled="1" valuesEnabled="1"><itemDefinition><addAllowed>0</addAllowed><hideAllowed>1</hideAllowed><modifyAllowed>1</modifyAllowed></itemDefinition><itemNames><itemName personalForm="0" lang="de">Ist offen für Besonderheiten einzelner Menschen (KG).</itemName></itemNames><itemDescriptions><itemDescription personalForm="0" lang="de">KG</itemDescription></itemDescriptions></gridItem><gridItem key="AVZ8RXIYC078" itemKind="indicator" countEnabled="1" valuesEnabled="1"><itemDefinition><addAllowed>0</addAllowed><hideAllowed>1</hideAllowed><modifyAllowed>1</modifyAllowed></itemDefinition><itemNames><itemName personalForm="0" lang="de">Erkennt und akzeptiert Unterschiede (KG).</itemName></itemNames><itemDescriptions><itemDescription personalForm="0" lang="de">KG</itemDescription></itemDescriptions></gridItem></gridItems></gridItem></gridItems></gridItem><gridItem key="AVZ8RXIZMJ80" itemKind="competencearea" countEnabled="0" valuesEnabled="0"><itemDefinition><addAllowed>0</addAllowed><hideAllowed>0</hideAllowed><modifyAllowed>0</modifyAllowed></itemDefinition><itemNames><itemName personalForm="0" lang="de">Sachkompetenz</itemName></itemNames><gridItems><gridItem key="AVZ8RXIZS482" itemKind="target" countEnabled="1" valuesEnabled="1"><itemDefinition><addAllowed>1</addAllowed><hideAllowed>1</hideAllowed><modifyAllowed>1</modifyAllowed></itemDefinition><itemNames><itemName personalForm="0" lang="de">Umgang mit Materialien</itemName></itemNames><gridItems><gridItem key="AVZ8RXIZX384" itemKind="indicator" countEnabled="1" valuesEnabled="1"><itemDefinition><addAllowed>0</addAllowed><hideAllowed>1</hideAllowed><modifyAllowed>1</modifyAllowed></itemDefinition><itemNames><itemName personalForm="0" lang="de">Kennt eingeführte Techniken und kann sie anwenden (malen, schneiden...) (KG).</itemName></itemNames><itemDescriptions><itemDescription personalForm="0" lang="de">KG</itemDescription></itemDescriptions></gridItem><gridItem key="AVZ8RXJACU86" itemKind="indicator" countEnabled="1" valuesEnabled="1"><itemDefinition><addAllowed>0</addAllowed><hideAllowed>1</hideAllowed><modifyAllowed>1</modifyAllowed></itemDefinition><itemNames><itemName personalForm="0" lang="de">Kann bekannte Werkzeuge und Geräte richtig handhaben (KG).</itemName></itemNames><itemDescriptions><itemDescription personalForm="0" lang="de">KG</itemDescription></itemDescriptions></gridItem><gridItem key="AVZ8RXJAGU88" itemKind="indicator" countEnabled="1" valuesEnabled="1"><itemDefinition><addAllowed>0</addAllowed><hideAllowed>1</hideAllowed><modifyAllowed>1</modifyAllowed></itemDefinition><itemNames><itemName personalForm="0" lang="de">Kann Materialien, die es kennen gelernt hat, sinnvoll verwenden (KG).</itemName></itemNames><itemDescriptions><itemDescription personalForm="0" lang="de">KG</itemDescription></itemDescriptions></gridItem></gridItems></gridItem><gridItem key="AVZ8RXJALB90" itemKind="target" countEnabled="1" valuesEnabled="1"><itemDefinition><addAllowed>1</addAllowed><hideAllowed>1</hideAllowed><modifyAllowed>1</modifyAllowed></itemDefinition><itemNames><itemName personalForm="0" lang="de">Kulturelle Erfahrungen</itemName></itemNames><gridItems><gridItem key="AVZ8RXJARM92" itemKind="indicator" countEnabled="1" valuesEnabled="1"><itemDefinition><addAllowed>0</addAllowed><hideAllowed>1</hideAllowed><modifyAllowed>1</modifyAllowed></itemDefinition><itemNames><itemName personalForm="0" lang="de">Hat Kenntnis von Bräuchen und Feiern in seiner näheren Umgebung (KG).</itemName></itemNames><itemDescriptions><itemDescription personalForm="0" lang="de">KG</itemDescription></itemDescriptions></gridItem><gridItem key="AVZ8RXJAVQ94" itemKind="indicator" countEnabled="1" valuesEnabled="1"><itemDefinition><addAllowed>0</addAllowed><hideAllowed>1</hideAllowed><modifyAllowed>1</modifyAllowed></itemDefinition><itemNames><itemName personalForm="0" lang="de">Kennt sich in der näheren Umgebung aus und kann sich darin orientieren (KG).</itemName></itemNames><itemDescriptions><itemDescription personalForm="0" lang="de">KG</itemDescription></itemDescriptions></gridItem></gridItems></gridItem><gridItem key="AVZ8RXJAAV96" itemKind="target" countEnabled="1" valuesEnabled="1"><itemDefinition><addAllowed>1</addAllowed><hideAllowed>1</hideAllowed><modifyAllowed>1</modifyAllowed></itemDefinition><itemNames><itemName personalForm="0" lang="de">Wahrnehmung von Vorgängen in der Umwelt</itemName></itemNames><gridItems><gridItem key="AVZ8RXJAER98" itemKind="indicator" countEnabled="1" valuesEnabled="1"><itemDefinition><addAllowed>0</addAllowed><hideAllowed>1</hideAllowed><modifyAllowed>1</modifyAllowed></itemDefinition><itemNames><itemName personalForm="0" lang="de">Zeigt Interesse an der Umwelt (Menschen, Tiere Natur) (KG).</itemName></itemNames><itemDescriptions><itemDescription personalForm="0" lang="de">KG</itemDescription></itemDescriptions></gridItem><gridItem key="AVZ8RXJAI2100" itemKind="indicator" countEnabled="1" valuesEnabled="1"><itemDefinition><addAllowed>0</addAllowed><hideAllowed>1</hideAllowed><modifyAllowed>1</modifyAllowed></itemDefinition><itemNames><itemName personalForm="0" lang="de">Nimmt Entwicklungen und Veränderungen wahr und erkennt Zusammenhänge (KG).</itemName></itemNames><itemDescriptions><itemDescription personalForm="0" lang="de">KG</itemDescription></itemDescriptions></gridItem><gridItem key="AVZ8RXJAL5102" itemKind="indicator" countEnabled="1" valuesEnabled="1"><itemDefinition><addAllowed>0</addAllowed><hideAllowed>1</hideAllowed><modifyAllowed>1</modifyAllowed></itemDefinition><itemNames><itemName personalForm="0" lang="de">Zeigt Einfühlungsvermögen und Sorgfalt (KG).</itemName></itemNames><itemDescriptions><itemDescription personalForm="0" lang="de">KG</itemDescription></itemDescriptions></gridItem></gridItems></gridItem><gridItem key="AVZ8RXJAPA104" itemKind="target" countEnabled="1" valuesEnabled="1"><itemDefinition><addAllowed>1</addAllowed><hideAllowed>1</hideAllowed><modifyAllowed>1</modifyAllowed></itemDefinition><itemNames><itemName personalForm="0" lang="de">Entwicklung von Begriffen</itemName></itemNames><gridItems><gridItem key="AVZ8RXJATZ106" itemKind="indicator" countEnabled="1" valuesEnabled="1"><itemDefinition><addAllowed>0</addAllowed><hideAllowed>1</hideAllowed><modifyAllowed>1</modifyAllowed></itemDefinition><itemNames><itemName personalForm="0" lang="de">Kann Gegenstände und Lebewesen richtig benennen und ordnen (nach Oberbegriffen und Gegensätzen) (KG).</itemName></itemNames><itemDescriptions><itemDescription personalForm="0" lang="de">KG</itemDescription></itemDescriptions></gridItem><gridItem key="AVZ8RXJAWI108" itemKind="indicator" countEnabled="1" valuesEnabled="1"><itemDefinition><addAllowed>0</addAllowed><hideAllowed>1</hideAllowed><modifyAllowed>1</modifyAllowed></itemDefinition><itemNames><itemName personalForm="0" lang="de">Schildert Sachverhalte und Abläufe allgemein verständlich (KG).</itemName></itemNames><itemDescriptions><itemDescription personalForm="0" lang="de">KG</itemDescription></itemDescriptions></gridItem><gridItem key="AVZ8RXJBB8110" itemKind="indicator" countEnabled="1" valuesEnabled="1"><itemDefinition><addAllowed>0</addAllowed><hideAllowed>1</hideAllowed><modifyAllowed>1</modifyAllowed></itemDefinition><itemNames><itemName personalForm="0" lang="de">Versteht Zeichen und Symbole (z.B. Verkehrszeichen, Zeichnungen auf Schildern aus seiner Umgebung) (KG).</itemName></itemNames><itemDescriptions><itemDescription personalForm="0" lang="de">KG</itemDescription></itemDescriptions></gridItem></gridItems></gridItem><gridItem key="AVZ8RXJBG5112" itemKind="target" countEnabled="1" valuesEnabled="1"><itemDefinition><addAllowed>1</addAllowed><hideAllowed>1</hideAllowed><modifyAllowed>1</modifyAllowed></itemDefinition><itemNames><itemName personalForm="0" lang="de">Sprachverhalten</itemName></itemNames><gridItems><gridItem key="AVZ8RXJBJW114" itemKind="indicator" countEnabled="1" valuesEnabled="1"><itemDefinition><addAllowed>0</addAllowed><hideAllowed>1</hideAllowed><modifyAllowed>1</modifyAllowed></itemDefinition><itemNames><itemName personalForm="0" lang="de">Verfügt über einen altersgemässen Wortschatz (KG).</itemName></itemNames><itemDescriptions><itemDescription personalForm="0" lang="de">KG</itemDescription></itemDescriptions></gridItem><gridItem key="AVZ8RXJBM3116" itemKind="indicator" countEnabled="1" valuesEnabled="1"><itemDefinition><addAllowed>0</addAllowed><hideAllowed>1</hideAllowed><modifyAllowed>1</modifyAllowed></itemDefinition><itemNames><itemName personalForm="0" lang="de">Spricht deutlich und in vollen Sätzen (KG).</itemName></itemNames><itemDescriptions><itemDescription personalForm="0" lang="de">KG</itemDescription></itemDescriptions></gridItem><gridItem key="AVZ8RXJBQ6118" itemKind="indicator" countEnabled="1" valuesEnabled="1"><itemDefinition><addAllowed>0</addAllowed><hideAllowed>1</hideAllowed><modifyAllowed>1</modifyAllowed></itemDefinition><itemNames><itemName personalForm="0" lang="de">Kann einfache Gedichte und Lieder auswendig (KG).</itemName></itemNames><itemDescriptions><itemDescription personalForm="0" lang="de">KG</itemDescription></itemDescriptions></gridItem><gridItem key="AVZ8RXJBTB120" itemKind="indicator" countEnabled="1" valuesEnabled="1"><itemDefinition><addAllowed>0</addAllowed><hideAllowed>1</hideAllowed><modifyAllowed>1</modifyAllowed></itemDefinition><itemNames><itemName personalForm="0" lang="de">Erzählt verständlich und in nachvollziehbarer Reihenfolge (KG).</itemName></itemNames><itemDescriptions><itemDescription personalForm="0" lang="de">KG</itemDescription></itemDescriptions></gridItem><gridItem key="AVZ8RXJBWW122" itemKind="indicator" countEnabled="1" valuesEnabled="1"><itemDefinition><addAllowed>0</addAllowed><hideAllowed>1</hideAllowed><modifyAllowed>1</modifyAllowed></itemDefinition><itemNames><itemName personalForm="0" lang="de">Beteiligt sich an Gesprächen (KG).</itemName></itemNames><itemDescriptions><itemDescription personalForm="0" lang="de">KG</itemDescription></itemDescriptions></gridItem></gridItems></gridItem><gridItem key="AVZ8RXJBBX124" itemKind="target" countEnabled="1" valuesEnabled="1"><itemDefinition><addAllowed>1</addAllowed><hideAllowed>1</hideAllowed><modifyAllowed>1</modifyAllowed></itemDefinition><itemNames><itemName personalForm="0" lang="de">Problemlösungs-verhalten</itemName></itemNames><gridItems><gridItem key="AVZ8RXJBG2126" itemKind="indicator" countEnabled="1" valuesEnabled="1"><itemDefinition><addAllowed>0</addAllowed><hideAllowed>1</hideAllowed><modifyAllowed>1</modifyAllowed></itemDefinition><itemNames><itemName personalForm="0" lang="de">Hat Freude am Ausprobieren und Forschen (KG).</itemName></itemNames><itemDescriptions><itemDescription personalForm="0" lang="de">KG</itemDescription></itemDescriptions></gridItem><gridItem key="AVZ8RXJBII128" itemKind="indicator" countEnabled="1" valuesEnabled="1"><itemDefinition><addAllowed>0</addAllowed><hideAllowed>1</hideAllowed><modifyAllowed>1</modifyAllowed></itemDefinition><itemNames><itemName personalForm="0" lang="de">Hat Ideen für die Lösung einer Aufgabe (KG).</itemName></itemNames><itemDescriptions><itemDescription personalForm="0" lang="de">KG</itemDescription></itemDescriptions></gridItem><gridItem key="AVZ8RXJBMR130" itemKind="indicator" countEnabled="1" valuesEnabled="1"><itemDefinition><addAllowed>0</addAllowed><hideAllowed>1</hideAllowed><modifyAllowed>1</modifyAllowed></itemDefinition><itemNames><itemName personalForm="0" lang="de">Kann bekannte Techniken und Materialien in neuen Situationen anwenden (KG).</itemName></itemNames><itemDescriptions><itemDescription personalForm="0" lang="de">KG</itemDescription></itemDescriptions></gridItem></gridItems></gridItem><gridItem key="AVZ8RXJBPX132" itemKind="target" countEnabled="1" valuesEnabled="1"><itemDefinition><addAllowed>1</addAllowed><hideAllowed>1</hideAllowed><modifyAllowed>1</modifyAllowed></itemDefinition><itemNames><itemName personalForm="0" lang="de">Erfassen von Beziehungen und Gesetzmässigkeiten</itemName></itemNames><gridItems><gridItem key="AVZ8RXJBT1134" itemKind="indicator" countEnabled="1" valuesEnabled="1"><itemDefinition><addAllowed>0</addAllowed><hideAllowed>1</hideAllowed><modifyAllowed>1</modifyAllowed></itemDefinition><itemNames><itemName personalForm="0" lang="de">Erkennt Muster oder Reihen und kann sie weiterführen (KG).</itemName></itemNames><itemDescriptions><itemDescription personalForm="0" lang="de">KG</itemDescription></itemDescriptions></gridItem><gridItem key="AVZ8RXJBXV136" itemKind="indicator" countEnabled="1" valuesEnabled="1"><itemDefinition><addAllowed>0</addAllowed><hideAllowed>1</hideAllowed><modifyAllowed>1</modifyAllowed></itemDefinition><itemNames><itemName personalForm="0" lang="de">Erkennt und erfasst einfache Mengenbilder (z.B. Würfelzahlen) (KG).</itemName></itemNames><itemDescriptions><itemDescription personalForm="0" lang="de">KG</itemDescription></itemDescriptions></gridItem><gridItem key="AVZ8RXJCBI138" itemKind="indicator" countEnabled="1" valuesEnabled="1"><itemDefinition><addAllowed>0</addAllowed><hideAllowed>1</hideAllowed><modifyAllowed>1</modifyAllowed></itemDefinition><itemNames><itemName personalForm="0" lang="de">Nimmt Zeitabschnitte wahr und entwickelt ein Zeitgefühl (KG).</itemName></itemNames><itemDescriptions><itemDescription personalForm="0" lang="de">KG</itemDescription></itemDescriptions></gridItem><gridItem key="AVZ8RXJCHC140" itemKind="indicator" countEnabled="1" valuesEnabled="1"><itemDefinition><addAllowed>0</addAllowed><hideAllowed>1</hideAllowed><modifyAllowed>1</modifyAllowed></itemDefinition><itemNames><itemName personalForm="0" lang="de">Kann geometrische Formen ordnen (KG).</itemName></itemNames><itemDescriptions><itemDescription personalForm="0" lang="de">KG</itemDescription></itemDescriptions></gridItem></gridItems></gridItem><gridItem key="AVZ8RXJCMS142" itemKind="target" countEnabled="1" valuesEnabled="1"><itemDefinition><addAllowed>1</addAllowed><hideAllowed>1</hideAllowed><modifyAllowed>1</modifyAllowed></itemDefinition><itemNames><itemName personalForm="0" lang="de">Merk- und Wiedergabefähigkeit</itemName></itemNames><gridItems><gridItem key="AVZ8RXJCQJ144" itemKind="indicator" countEnabled="1" valuesEnabled="1"><itemDefinition><addAllowed>0</addAllowed><hideAllowed>1</hideAllowed><modifyAllowed>1</modifyAllowed></itemDefinition><itemNames><itemName personalForm="0" lang="de">Kann sich Aufgaben, Regeln und Erfahrungen merken (KG).</itemName></itemNames><itemDescriptions><itemDescription personalForm="0" lang="de">KG</itemDescription></itemDescriptions></gridItem><gridItem key="AVZ8RXJCT7146" itemKind="indicator" countEnabled="1" valuesEnabled="1"><itemDefinition><addAllowed>0</addAllowed><hideAllowed>1</hideAllowed><modifyAllowed>1</modifyAllowed></itemDefinition><itemNames><itemName personalForm="0" lang="de">Kann sich an Geschichten, Lieder und Verse erinnern (KG).</itemName></itemNames><itemDescriptions><itemDescription personalForm="0" lang="de">KG</itemDescription></itemDescriptions></gridItem><gridItem key="AVZ8RXJCWC148" itemKind="indicator" countEnabled="1" valuesEnabled="1"><itemDefinition><addAllowed>0</addAllowed><hideAllowed>1</hideAllowed><modifyAllowed>1</modifyAllowed></itemDefinition><itemNames><itemName personalForm="0" lang="de">Findet Materialien und Orte im Kindergarten wieder (KG).</itemName></itemNames><itemDescriptions><itemDescription personalForm="0" lang="de">KG</itemDescription></itemDescriptions></gridItem><gridItem key="AVZ8RXJDAU150" itemKind="indicator" countEnabled="1" valuesEnabled="1"><itemDefinition><addAllowed>0</addAllowed><hideAllowed>1</hideAllowed><modifyAllowed>1</modifyAllowed></itemDefinition><itemNames><itemName personalForm="0" lang="de">Ist aufmerksam bei Geschichten und Erklärungen (KG).</itemName></itemNames><itemDescriptions><itemDescription personalForm="0" lang="de">KG</itemDescription></itemDescriptions></gridItem></gridItems></gridItem></gridItems></gridItem></gridItems></competenceGrid></competenceGrids></definitions></lehreroffice>
